sitemappy/__init__.py
sitemappy/__main__.py
sitemappy/crawler.py
sitemappy/link_scraper.py
sitemappy/main.py
sitemappy/py.typed
sitemappy_cli-1.0.5.dist-info/METADATA
sitemappy_cli-1.0.5.dist-info/WHEEL
sitemappy_cli-1.0.5.dist-info/entry_points.txt
sitemappy_cli-1.0.5.dist-info/RECORD
