Metadata-Version: 2.1
Name: sitemappy-cli
Version: 1.0.5
Summary: A Python library for crawling a website and returning a sitemap.
Author-Email: Daniel Wilton <daniel.wilton.dw@outlook.com>
License: MIT
Requires-Python: >=3.12
Requires-Dist: typer[all]>=0.12.3
Requires-Dist: validators>=0.28.3
Requires-Dist: httpx>=0.27.0
Requires-Dist: beautifulsoup4>=4.12.3
